setup.py
mindsflow_api/__init__.py
mindsflow_api.egg-info/PKG-INFO
mindsflow_api.egg-info/SOURCES.txt
mindsflow_api.egg-info/dependency_links.txt
mindsflow_api.egg-info/requires.txt
mindsflow_api.egg-info/top_level.txt
mindsflow_api/models/__init__.py
mindsflow_api/models/chat.py
mindsflow_api/models/history.py
mindsflow_api/models/model.py
mindsflow_api/utils/__init__.py
mindsflow_api/utils/http_request.py