Metadata-Version: 2.1
Name: mindsflow-api
Version: 0.0.3
Summary: A Python library for mindsflow.ai api
Author: Shawn-Tam
Author-email: shawn@mindsflow.ai
Classifier: Development Status :: 4 - Beta
Classifier: Intended Audience :: Developers
Classifier: License :: OSI Approved :: MIT License
Classifier: Programming Language :: Python :: 3.9
Classifier: Programming Language :: Python :: 3.10
Classifier: Programming Language :: Python :: 3.11
Requires-Dist: requests
Requires-Dist: httpx
Requires-Dist: redis
